[
 {
  "id": "87be550919804fa9",
  "title": "Quantitative structure-inhibitory activity relationships of substituted phenols onbacillus subtilis spore germination",
  "authors": [
   "Ming‐Ju Huang",
   "Nicholas Bodor"
  ],
  "journal": "International Journal of Quantum Chemistry",
  "publisher": "Wiley",
  "published": "1994-02-12",
  "year": 1994,
  "doi": "10.1002/qua.560520714",
  "url": "https://doi.org/10.1002/qua.560520714",
  "source": "openalex",
  "categories": [
   "Drug Discovery Chemistry",
   "Cheminformatics"
  ],
  "tags": [
   "Molecules",
   "QSAR",
   "SAR"
  ],
  "relevance_score": 66,
  "affiliations": [],
  "added": "2026-07-21"
 },
 {
  "id": "ce7c8215b3e0ef5d",
  "title": "Evaluation of the toxicity and quantitative structure - activity Relationships (QSAR) of chlorophenols to the copepodid stage of a marine copepod (Tisbe battagliai) and two species of benthic flatfish, the flounder (Platichthys flesus) and sole (Solea solea)",
  "authors": [
   "Steven G. Smith",
   "V.J. Furay",
   "P. J. Layiwola",
   "José A. Menezes‐Filho"
  ],
  "journal": "Chemosphere",
  "publisher": "Elsevier BV",
  "published": "1994-02-01",
  "year": 1994,
  "doi": "10.1016/0045-6535(94)90234-8",
  "url": "https://doi.org/10.1016/0045-6535(94)90234-8",
  "source": "openalex",
  "categories": [
   "Cheminformatics"
  ],
  "tags": [
   "QSAR"
  ],
  "relevance_score": 52,
  "affiliations": [
   "King's College London",
   "Lambeth Council",
   "Hospital São Rafael"
  ],
  "added": "2026-07-21"
 },
 {
  "id": "9f8c81976330f0df",
  "title": "A quantitative structure-activity relationship (QSAR) investigation of a Draize eye irritation database",
  "authors": [
   "M Cronin",
   "David A. Basketter",
   "Michael York"
  ],
  "journal": "Toxicology in Vitro",
  "publisher": "Elsevier BV",
  "published": "1994-02-01",
  "year": 1994,
  "doi": "10.1016/0887-2333(94)90204-6",
  "url": "https://doi.org/10.1016/0887-2333(94)90204-6",
  "source": "openalex",
  "categories": [
   "Drug Discovery Chemistry",
   "Cheminformatics"
  ],
  "tags": [
   "QSAR",
   "SAR"
  ],
  "relevance_score": 55,
  "affiliations": [
   "Liverpool John Moores University",
   "Unilever (United Kingdom)"
  ],
  "added": "2026-07-21"
 },
 {
  "id": "9396428c9363cce2",
  "title": "QSAR and Molecular Shape Analyses of Three Series of 1-(Phenylcarbamoyl)-2-pyrazoline Insecticides",
  "authors": [
   "Kathleen A. Rowberg",
   "Mark A. Even",
   "Éric Martin",
   "A. J. Hopfinger"
  ],
  "journal": "Journal of Agricultural and Food Chemistry",
  "publisher": "American Chemical Society",
  "published": "1994-02-01",
  "year": 1994,
  "doi": "10.1021/jf00038a027",
  "url": "https://doi.org/10.1021/jf00038a027",
  "source": "openalex",
  "categories": [
   "Cheminformatics"
  ],
  "tags": [
   "Molecules",
   "QSAR"
  ],
  "relevance_score": 48,
  "affiliations": [],
  "added": "2026-07-21"
 },
 {
  "id": "932ae8409a3a8f0f",
  "title": "Acridones and quinolones as inhibitors of ubiquinone functions in the mitochondrial respiratory chain",
  "authors": [
   "Walter Oettmeier",
   "Klaus Masson",
   "Michael Soll",
   "Ellen Reil"
  ],
  "journal": "Biochemical Society Transactions",
  "publisher": "Portland Press",
  "published": "1994-02-01",
  "year": 1994,
  "doi": "10.1042/bst0220213",
  "url": "https://doi.org/10.1042/bst0220213",
  "source": "openalex",
  "categories": [
   "Drug Discovery Chemistry",
   "Cheminformatics"
  ],
  "tags": [
   "QSAR",
   "SAR"
  ],
  "relevance_score": 60,
  "affiliations": [
   "Ruhr University Bochum"
  ],
  "added": "2026-07-21"
 },
 {
  "id": "92afb6fa3f7cd9e9",
  "title": "QSARs for photoinduced toxicity: I. Acute lethality of polycyclic aromatic hydrocarbons to Daphnia magna",
  "authors": [
   "Ovanes Mekenyan",
   "Gerald T. Ankley",
   "Gilman D. Veith",
   "Daniel J. Call"
  ],
  "journal": "Chemosphere",
  "publisher": "Elsevier BV",
  "published": "1994-02-01",
  "year": 1994,
  "doi": "10.1016/0045-6535(94)90299-2",
  "url": "https://doi.org/10.1016/0045-6535(94)90299-2",
  "source": "openalex",
  "categories": [
   "Cheminformatics"
  ],
  "tags": [
   "QSAR"
  ],
  "relevance_score": 52,
  "affiliations": [
   "Institute of Chemical Engineering",
   "University of Wisconsin–Superior",
   "Environmental Protection Agency"
  ],
  "added": "2026-07-21"
 },
 {
  "id": "4c899e5504c53b54",
  "title": "Two million rodent carcinogens? The role of SAR and QSAR in their detection",
  "authors": [
   "John Ashby"
  ],
  "journal": "Mutation research. Fundamental and molecular mechanisms of mutagenesis",
  "publisher": "",
  "published": "1994-02-01",
  "year": 1994,
  "doi": "10.1016/0027-5107(94)90122-8",
  "url": "https://doi.org/10.1016/0027-5107(94)90122-8",
  "source": "openalex",
  "categories": [
   "Cheminformatics"
  ],
  "tags": [
   "QSAR"
  ],
  "relevance_score": 52,
  "affiliations": [
   "AstraZeneca (United Kingdom)"
  ],
  "added": "2026-07-21"
 }
]