[
 {
  "id": "6dc10d8fdf26c76e",
  "title": "Analysis of the electrical properties of PZT by a BP artificial neural network",
  "authors": [
   "Kai Cai",
   "Juntao Xia",
   "Longtu Li",
   "Zhilun Gui"
  ],
  "journal": "Computational Materials Science",
  "publisher": "Elsevier BV",
  "published": "2005-02-11",
  "year": 2005,
  "doi": "10.1016/j.commatsci.2004.12.066",
  "url": "https://doi.org/10.1016/j.commatsci.2004.12.066",
  "source": "openalex",
  "categories": [
   "Deep Learning"
  ],
  "tags": [
   "Neural Network"
  ],
  "relevance_score": 48,
  "affiliations": [
   "Tsinghua University",
   "Beijing Institute of Technology"
  ],
  "added": "2026-07-21"
 },
 {
  "id": "52319861b8d0ad70",
  "title": "Classifying ‘Drug-likeness' with Kernel-Based Learning Methods",
  "authors": [
   "Klaus‐Robert Müller",
   "Gunnar Rätsch",
   "Sören Sonnenburg",
   "Sebastian Mika",
   "Michael Grimm",
   "Nikolaus Heinrich"
  ],
  "journal": "Journal of Chemical Information and Modeling",
  "publisher": "American Chemical Society",
  "published": "2005-02-08",
  "year": 2005,
  "doi": "10.1021/ci049737o",
  "url": "https://doi.org/10.1021/ci049737o",
  "source": "openalex",
  "categories": [
   "Computational Chemistry",
   "Drug Discovery Chemistry",
   "Machine Learning",
   "Classical ML"
  ],
  "tags": [
   "Chemistry",
   "Computational Chemistry",
   "Drug Discovery",
   "Machine Learning",
   "SVM"
  ],
  "relevance_score": 79,
  "affiliations": [
   "Max Planck Society",
   "University of Potsdam",
   "Friedrich Miescher Laboratory"
  ],
  "added": "2026-07-21"
 }
]